zospy/__init__.py
zospy/zpcore.py
zospy/analyses/__init__.py
zospy/analyses/base.py
zospy/analyses/decorators.py
zospy/analyses/extendedscene/__init__.py
zospy/analyses/extendedscene/geometric_image_analysis.py
zospy/analyses/mtf/__init__.py
zospy/analyses/mtf/fft_mtf.py
zospy/analyses/mtf/fft_through_focus_mtf.py
zospy/analyses/mtf/huygens_mtf.py
zospy/analyses/old/__init__.py
zospy/analyses/old/base.py
zospy/analyses/old/extendedscene.py
zospy/analyses/old/mtf.py
zospy/analyses/old/physicaloptics.py
zospy/analyses/old/polarization.py
zospy/analyses/old/psf.py
zospy/analyses/old/raysandspots.py
zospy/analyses/old/reports.py
zospy/analyses/old/surface.py
zospy/analyses/old/systemviewers.py
zospy/analyses/old/wavefront.py
zospy/analyses/parsers/__init__.py
zospy/analyses/parsers/base.py
zospy/analyses/parsers/transformers.py
zospy/analyses/parsers/types.py
zospy/analyses/parsers/grammars/__init__.py
zospy/analyses/parsers/grammars/cardinal_points.lark
zospy/analyses/parsers/grammars/polarization_pupil_map.lark
zospy/analyses/parsers/grammars/polarization_transmission.lark
zospy/analyses/parsers/grammars/single_ray_trace.lark
zospy/analyses/parsers/grammars/surface_data.lark
zospy/analyses/parsers/grammars/system_data.lark
zospy/analyses/parsers/grammars/zernike_standard_coefficients.lark
zospy/analyses/parsers/grammars/zospy.lark
zospy/analyses/physicaloptics/__init__.py
zospy/analyses/physicaloptics/physical_optics_propagation.py
zospy/analyses/polarization/__init__.py
zospy/analyses/polarization/pupil_map.py
zospy/analyses/polarization/transmission.py
zospy/analyses/psf/__init__.py
zospy/analyses/psf/fft_psf.py
zospy/analyses/psf/huygens_psf.py
zospy/analyses/raysandspots/__init__.py
zospy/analyses/raysandspots/ray_fan.py
zospy/analyses/raysandspots/single_ray_trace.py
zospy/analyses/reports/__init__.py
zospy/analyses/reports/cardinal_points.py
zospy/analyses/reports/surface_data.py
zospy/analyses/reports/system_data.py
zospy/analyses/surface/__init__.py
zospy-2.1.3.dist-info/METADATA
zospy-2.1.3.dist-info/WHEEL
zospy-2.1.3.dist-info/licenses/LICENSE.txt
zospy-2.1.3.dist-info/RECORD
