Metadata-Version: 2.4
Name: zospy
Version: 2.1.3
Summary: A Python package used to communicate with Zemax OpticStudio through the API
Project-URL: Source, https://github.com/MREYE-LUMC/ZOSPy
Project-URL: Documentation, https://mreye-lumc.github.io/ZOSPy
Author: Luc van Vught, Jan-Willem Beenakker, Corné Haasjes
Maintainer-email: MReye research group <zospy@mreye.nl>
License: MIT License
License-File: LICENSE.txt
Keywords: API,OpticStudio,ZOSAPI,Zemax
Classifier: Development Status :: 5 - Production/Stable
Classifier: Programming Language :: Python :: 3
Classifier: Typing :: Typed
Requires-Python: <3.14,>=3.10
Requires-Dist: lark~=1.2.0
Requires-Dist: numpy
Requires-Dist: pandas
Requires-Dist: pydantic>=2.4.0
Requires-Dist: pythonnet<4,>=3.0.0
Requires-Dist: semver<4,>=3.0.0
Requires-Dist: typing-extensions; python_version <= '3.10'
Provides-Extra: docs
Requires-Dist: ipython; extra == 'docs'
Requires-Dist: myst-parser; extra == 'docs'
Requires-Dist: nbsphinx; extra == 'docs'
Requires-Dist: numpydoc; extra == 'docs'
Requires-Dist: sphinx; extra == 'docs'
Requires-Dist: sphinx-book-theme; extra == 'docs'
Requires-Dist: sphinx-design; extra == 'docs'
